{
  "$schema": "https://json.schemastore.org/tsconfig",
  "display": "Express.js",
  "compilerOptions": {
    "allowJs": true,
    "allowSyntheticDefaultImports": true,
    "checkJs": true,
    "esModuleInterop": true,
    "forceConsistentCasingInFileNames": true,
    "isolatedModules": true,
    "moduleDetection": "force",
    "noUncheckedIndexedAccess": true,
    "resolveJsonModule": true,
    "skipLibCheck": true,
    "strict": true,
    "strictNullChecks": true,
    "target": "ES2022",
    "verbatimModuleSyntax": true
  }
}
